{
  "annotations": {
    "list": [
      {
        "builtIn": 1,
        "datasource": "-- Grafana --",
        "enable": true,
        "hide": true,
        "iconColor": "rgba(0, 211, 255, 1)",
        "name": "Annotations & Alerts",
        "target": {
          "limit": 100,
          "matchAny": false,
          "tags": [],
          "type": "dashboard"
        },
        "type": "dashboard"
      }
    ]
  },
  "editable": true,
  "fiscalYearStartMonth": 0,
  "gnetId": null,
  "graphTooltip": 0,
  "id": 6,
  "links": [],
  "liveNow": false,
  "panels": [
    {
      "collapsed": false,
      "datasource": null,
      "gridPos": {
        "h": 1,
        "w": 24,
        "x": 0,
        "y": 0
      },
      "id": 6,
      "panels": [],
      "title": "Get Scores",
      "type": "row"
    },
    {
      "datasource": "Prometheus",
      "fieldConfig": {
        "defaults": {
          "color": {
            "mode": "palette-classic"
          },
          "custom": {
            "axisLabel": "",
            "axisPlacement": "auto",
            "barAlignment": 0,
            "drawStyle": "line",
            "fillOpacity": 0,
            "gradientMode": "none",
            "hideFrom": {
              "legend": false,
              "tooltip": false,
              "viz": false
            },
            "lineInterpolation": "linear",
            "lineWidth": 1,
            "pointSize": 5,
            "scaleDistribution": {
              "type": "linear"
            },
            "showPoints": "auto",
            "spanNulls": false,
            "stacking": {
              "group": "A",
              "mode": "none"
            },
            "thresholdsStyle": {
              "mode": "off"
            }
          },
          "mappings": [],
          "thresholds": {
            "mode": "absolute",
            "steps": [
              {
                "color": "green",
                "value": null
              },
              {
                "color": "red",
                "value": 80
              }
            ]
          }
        },
        "overrides": []
      },
      "gridPos": {
        "h": 9,
        "w": 12,
        "x": 0,
        "y": 1
      },
      "id": 16,
      "options": {
        "legend": {
          "calcs": [],
          "displayMode": "hidden",
          "placement": "bottom"
        },
        "tooltip": {
          "mode": "single"
        }
      },
      "targets": [
        {
          "exemplar": true,
          "expr": "sum(increase(gorse_cache_get_scores_seconds_count{}[10m]))",
          "interval": "",
          "legendFormat": "",
          "refId": "A"
        }
      ],
      "title": "Get Scores Count (10 Minutes)",
      "type": "timeseries"
    },
    {
      "datasource": "Prometheus",
      "fieldConfig": {
        "defaults": {
          "color": {
            "mode": "palette-classic"
          },
          "custom": {
            "axisLabel": "",
            "axisPlacement": "auto",
            "barAlignment": 0,
            "drawStyle": "line",
            "fillOpacity": 0,
            "gradientMode": "none",
            "hideFrom": {
              "legend": false,
              "tooltip": false,
              "viz": false
            },
            "lineInterpolation": "linear",
            "lineWidth": 1,
            "pointSize": 5,
            "scaleDistribution": {
              "type": "linear"
            },
            "showPoints": "auto",
            "spanNulls": false,
            "stacking": {
              "group": "A",
              "mode": "none"
            },
            "thresholdsStyle": {
              "mode": "off"
            }
          },
          "mappings": [],
          "thresholds": {
            "mode": "absolute",
            "steps": [
              {
                "color": "green",
                "value": null
              },
              {
                "color": "red",
                "value": 80
              }
            ]
          }
        },
        "overrides": []
      },
      "gridPos": {
        "h": 9,
        "w": 12,
        "x": 12,
        "y": 1
      },
      "id": 4,
      "options": {
        "legend": {
          "calcs": [],
          "displayMode": "hidden",
          "placement": "bottom"
        },
        "tooltip": {
          "mode": "single"
        }
      },
      "targets": [
        {
          "exemplar": true,
          "expr": "histogram_quantile(0.99, sum by(le) (increase(gorse_cache_get_scores_seconds_bucket{}[10m])))",
          "interval": "",
          "legendFormat": "",
          "refId": "A"
        }
      ],
      "title": "Get Scores Latency (Quantile 0.99)",
      "type": "timeseries"
    },
    {
      "collapsed": false,
      "datasource": null,
      "gridPos": {
        "h": 1,
        "w": 24,
        "x": 0,
        "y": 10
      },
      "id": 11,
      "panels": [],
      "title": "Set Scores",
      "type": "row"
    },
    {
      "datasource": "Prometheus",
      "fieldConfig": {
        "defaults": {
          "color": {
            "mode": "palette-classic"
          },
          "custom": {
            "axisLabel": "",
            "axisPlacement": "auto",
            "barAlignment": 0,
            "drawStyle": "line",
            "fillOpacity": 0,
            "gradientMode": "none",
            "hideFrom": {
              "legend": false,
              "tooltip": false,
              "viz": false
            },
            "lineInterpolation": "linear",
            "lineWidth": 1,
            "pointSize": 5,
            "scaleDistribution": {
              "type": "linear"
            },
            "showPoints": "auto",
            "spanNulls": false,
            "stacking": {
              "group": "A",
              "mode": "none"
            },
            "thresholdsStyle": {
              "mode": "off"
            }
          },
          "mappings": [],
          "thresholds": {
            "mode": "absolute",
            "steps": [
              {
                "color": "green",
                "value": null
              },
              {
                "color": "red",
                "value": 80
              }
            ]
          }
        },
        "overrides": []
      },
      "gridPos": {
        "h": 9,
        "w": 12,
        "x": 0,
        "y": 11
      },
      "id": 8,
      "options": {
        "legend": {
          "calcs": [],
          "displayMode": "hidden",
          "placement": "bottom"
        },
        "tooltip": {
          "mode": "single"
        }
      },
      "targets": [
        {
          "exemplar": true,
          "expr": "sum(increase(gorse_cache_set_scores_seconds_count{}[10m]))",
          "interval": "",
          "legendFormat": "",
          "refId": "A"
        }
      ],
      "title": "Set Scores Count (10 Minutes)",
      "type": "timeseries"
    },
    {
      "datasource": "Prometheus",
      "fieldConfig": {
        "defaults": {
          "color": {
            "mode": "palette-classic"
          },
          "custom": {
            "axisLabel": "",
            "axisPlacement": "auto",
            "barAlignment": 0,
            "drawStyle": "line",
            "fillOpacity": 0,
            "gradientMode": "none",
            "hideFrom": {
              "legend": false,
              "tooltip": false,
              "viz": false
            },
            "lineInterpolation": "linear",
            "lineWidth": 1,
            "pointSize": 5,
            "scaleDistribution": {
              "type": "linear"
            },
            "showPoints": "auto",
            "spanNulls": false,
            "stacking": {
              "group": "A",
              "mode": "none"
            },
            "thresholdsStyle": {
              "mode": "off"
            }
          },
          "mappings": [],
          "thresholds": {
            "mode": "absolute",
            "steps": [
              {
                "color": "green",
                "value": null
              },
              {
                "color": "red",
                "value": 80
              }
            ]
          }
        },
        "overrides": []
      },
      "gridPos": {
        "h": 9,
        "w": 12,
        "x": 12,
        "y": 11
      },
      "id": 17,
      "options": {
        "legend": {
          "calcs": [],
          "displayMode": "hidden",
          "placement": "bottom"
        },
        "tooltip": {
          "mode": "single"
        }
      },
      "targets": [
        {
          "exemplar": true,
          "expr": "histogram_quantile(0.99, sum by(le) (increase(gorse_cache_set_scores_seconds_bucket{}[10m])))",
          "interval": "",
          "legendFormat": "",
          "refId": "A"
        }
      ],
      "title": "Set Scores Latency (Quantile 0.99)",
      "type": "timeseries"
    },
    {
      "collapsed": true,
      "datasource": null,
      "gridPos": {
        "h": 1,
        "w": 24,
        "x": 0,
        "y": 20
      },
      "id": 13,
      "panels": [
        {
          "datasource": "Prometheus",
          "fieldConfig": {
            "defaults": {
              "color": {
                "mode": "palette-classic"
              },
              "custom": {
                "axisLabel": "",
                "axisPlacement": "auto",
                "barAlignment": 0,
                "drawStyle": "line",
                "fillOpacity": 0,
                "gradientMode": "none",
                "hideFrom": {
                  "legend": false,
                  "tooltip": false,
                  "viz": false
                },
                "lineInterpolation": "linear",
                "lineWidth": 1,
                "pointSize": 5,
                "scaleDistribution": {
                  "type": "linear"
                },
                "showPoints": "auto",
                "spanNulls": false,
                "stacking": {
                  "group": "A",
                  "mode": "none"
                },
                "thresholdsStyle": {
                  "mode": "off"
                }
              },
              "mappings": [],
              "thresholds": {
                "mode": "absolute",
                "steps": [
                  {
                    "color": "green",
                    "value": null
                  },
                  {
                    "color": "red",
                    "value": 80
                  }
                ]
              }
            },
            "overrides": []
          },
          "gridPos": {
            "h": 9,
            "w": 12,
            "x": 0,
            "y": 4
          },
          "id": 2,
          "options": {
            "legend": {
              "calcs": [],
              "displayMode": "hidden",
              "placement": "bottom"
            },
            "tooltip": {
              "mode": "single"
            }
          },
          "targets": [
            {
              "exemplar": true,
              "expr": "sum(increase(gorse_cache_append_scores_seconds_count{}[10m]))",
              "interval": "",
              "legendFormat": "",
              "refId": "A"
            }
          ],
          "title": "Append Scores Count (10 Minutes)",
          "type": "timeseries"
        },
        {
          "datasource": "Prometheus",
          "fieldConfig": {
            "defaults": {
              "color": {
                "mode": "palette-classic"
              },
              "custom": {
                "axisLabel": "",
                "axisPlacement": "auto",
                "barAlignment": 0,
                "drawStyle": "line",
                "fillOpacity": 0,
                "gradientMode": "none",
                "hideFrom": {
                  "legend": false,
                  "tooltip": false,
                  "viz": false
                },
                "lineInterpolation": "linear",
                "lineWidth": 1,
                "pointSize": 5,
                "scaleDistribution": {
                  "type": "linear"
                },
                "showPoints": "auto",
                "spanNulls": false,
                "stacking": {
                  "group": "A",
                  "mode": "none"
                },
                "thresholdsStyle": {
                  "mode": "off"
                }
              },
              "mappings": [],
              "thresholds": {
                "mode": "absolute",
                "steps": [
                  {
                    "color": "green",
                    "value": null
                  },
                  {
                    "color": "red",
                    "value": 80
                  }
                ]
              }
            },
            "overrides": []
          },
          "gridPos": {
            "h": 9,
            "w": 12,
            "x": 12,
            "y": 4
          },
          "id": 9,
          "options": {
            "legend": {
              "calcs": [],
              "displayMode": "hidden",
              "placement": "bottom"
            },
            "tooltip": {
              "mode": "single"
            }
          },
          "targets": [
            {
              "exemplar": true,
              "expr": "histogram_quantile(0.99, sum by(le) (increase(gorse_cache_append_scores_seconds_bucket{}[10m])))",
              "interval": "",
              "legendFormat": "",
              "refId": "A"
            }
          ],
          "title": "Append Scores Latency (Quantile 0.99)",
          "type": "timeseries"
        }
      ],
      "title": "Append Scores",
      "type": "row"
    },
    {
      "collapsed": true,
      "datasource": null,
      "gridPos": {
        "h": 1,
        "w": 24,
        "x": 0,
        "y": 21
      },
      "id": 15,
      "panels": [
        {
          "datasource": "Prometheus",
          "fieldConfig": {
            "defaults": {
              "color": {
                "mode": "palette-classic"
              },
              "custom": {
                "axisLabel": "",
                "axisPlacement": "auto",
                "barAlignment": 0,
                "drawStyle": "line",
                "fillOpacity": 0,
                "gradientMode": "none",
                "hideFrom": {
                  "legend": false,
                  "tooltip": false,
                  "viz": false
                },
                "lineInterpolation": "linear",
                "lineWidth": 1,
                "pointSize": 5,
                "scaleDistribution": {
                  "type": "linear"
                },
                "showPoints": "auto",
                "spanNulls": false,
                "stacking": {
                  "group": "A",
                  "mode": "none"
                },
                "thresholdsStyle": {
                  "mode": "off"
                }
              },
              "mappings": [],
              "thresholds": {
                "mode": "absolute",
                "steps": [
                  {
                    "color": "green",
                    "value": null
                  },
                  {
                    "color": "red",
                    "value": 80
                  }
                ]
              }
            },
            "overrides": []
          },
          "gridPos": {
            "h": 9,
            "w": 12,
            "x": 0,
            "y": 1
          },
          "id": 18,
          "options": {
            "legend": {
              "calcs": [],
              "displayMode": "hidden",
              "placement": "bottom"
            },
            "tooltip": {
              "mode": "single"
            }
          },
          "targets": [
            {
              "exemplar": true,
              "expr": "sum(increase(gorse_cache_clear_scores_seconds_count{}[10m]))",
              "interval": "",
              "legendFormat": "",
              "refId": "A"
            }
          ],
          "title": "Clear Scores Count (10 Minutes)",
          "type": "timeseries"
        },
        {
          "datasource": "Prometheus",
          "fieldConfig": {
            "defaults": {
              "color": {
                "mode": "palette-classic"
              },
              "custom": {
                "axisLabel": "",
                "axisPlacement": "auto",
                "barAlignment": 0,
                "drawStyle": "line",
                "fillOpacity": 0,
                "gradientMode": "none",
                "hideFrom": {
                  "legend": false,
                  "tooltip": false,
                  "viz": false
                },
                "lineInterpolation": "linear",
                "lineWidth": 1,
                "pointSize": 5,
                "scaleDistribution": {
                  "type": "linear"
                },
                "showPoints": "auto",
                "spanNulls": false,
                "stacking": {
                  "group": "A",
                  "mode": "none"
                },
                "thresholdsStyle": {
                  "mode": "off"
                }
              },
              "mappings": [],
              "thresholds": {
                "mode": "absolute",
                "steps": [
                  {
                    "color": "green",
                    "value": null
                  },
                  {
                    "color": "red",
                    "value": 80
                  }
                ]
              }
            },
            "overrides": []
          },
          "gridPos": {
            "h": 9,
            "w": 12,
            "x": 12,
            "y": 1
          },
          "id": 19,
          "options": {
            "legend": {
              "calcs": [],
              "displayMode": "hidden",
              "placement": "bottom"
            },
            "tooltip": {
              "mode": "single"
            }
          },
          "targets": [
            {
              "exemplar": true,
              "expr": "histogram_quantile(0.99, sum by(le) (increase(gorse_cache_clear_scores_seconds_bucket{}[10m])))",
              "interval": "",
              "legendFormat": "",
              "refId": "A"
            }
          ],
          "title": "Clear Scores Latency (Quantile 0.99)",
          "type": "timeseries"
        }
      ],
      "title": "Clear Scores",
      "type": "row"
    }
  ],
  "refresh": "",
  "schemaVersion": 31,
  "style": "dark",
  "tags": [],
  "templating": {
    "list": []
  },
  "time": {
    "from": "now-6h",
    "to": "now"
  },
  "timepicker": {},
  "timezone": "",
  "title": "Gorse Cache",
  "uid": "IRbJCMK7z",
  "version": 8
}